intersection_grouper/LICENSE
intersection_grouper/README.MD
intersection_grouper/__init__.py
intersection_grouper/requirements.txt
intersection_grouper/thirdparty.json
intersection_grouper-0.11.dist-info/LICENSE.rst
intersection_grouper-0.11.dist-info/METADATA
intersection_grouper-0.11.dist-info/WHEEL
intersection_grouper-0.11.dist-info/top_level.txt
intersection_grouper-0.11.dist-info/RECORD
